main.py
wayspiritmcp_ppa-0.1.1.dist-info/METADATA
wayspiritmcp_ppa-0.1.1.dist-info/WHEEL
wayspiritmcp_ppa-0.1.1.dist-info/entry_points.txt
wayspiritmcp_ppa-0.1.1.dist-info/top_level.txt
wayspiritmcp_ppa-0.1.1.dist-info/RECORD
